<?xml version="1.0" encoding="UTF-8" standalone="yes"?>
<node artifactManager="be.nabu.eai.module.services.crud.CRUDArtifactManager" created="2023-06-21T14:54:17.138+02:00" lastModified="2023-06-21T15:23:44.611+02:00" leaf="false" version="5">
    <environmentId>apollo</environmentId>
    <hidden>false</hidden>
    <locked>false</locked>
    <properties/>
    <references>nabu.providers.testing.persisted.database.types.testCaseInstanceAttachment</references>
    <references>nabu.services.crud.provider.basic.provider</references>
</node>
